kissfix/__init__.py
kissfix/classes.py
kissfix/constants.py
kissfix/exceptions.py
kissfix/util.py
kissfix-7.0.11.dist-info/LICENSE
kissfix-7.0.11.dist-info/METADATA
kissfix-7.0.11.dist-info/WHEEL
kissfix-7.0.11.dist-info/top_level.txt
kissfix-7.0.11.dist-info/RECORD
