Metadata-Version: 2.1
Name: kissfix
Version: 7.0.11
Summary: Python KISS Module.
Home-page: https://github.com/xssfox/kiss-fix
Author: Greg Albrecht - patches by Michael Wheeler
Author-email: oss@undef.net
License: Copyright 2017 Greg Albrecht and Contributors
Requires-Dist: pyserial (>=3.4)
